gs_me/__init__.py
gs_me/run.py
gs_me/genomespy/index.html
gs_me/genomespy/script.js
gs_me/genomespy/style.css
gs_me-0.1.8.dist-info/LICENSE
gs_me-0.1.8.dist-info/METADATA
gs_me-0.1.8.dist-info/WHEEL
gs_me-0.1.8.dist-info/entry_points.txt
gs_me-0.1.8.dist-info/top_level.txt
gs_me-0.1.8.dist-info/RECORD
