Metadata-Version: 2.1
Name: gs-me
Version: 0.1.8
Summary: A genome visualization tool
Author-email: Dmitrii Utkin <dutking@gmail.com>
License: MIT License
Classifier: Development Status :: 3 - Alpha
Classifier: Programming Language :: Python :: 3
Classifier: License :: OSI Approved :: MIT License
Classifier: Operating System :: OS Independent
Requires-Python: >=3.9
License-File: LICENSE
